review_ingest_app/batch_builder.py
review_ingest_app/data/data_models.py
review_ingest_app/utils.py
review_ingest_app-1.0.1.dist-info/METADATA
review_ingest_app-1.0.1.dist-info/WHEEL
review_ingest_app-1.0.1.dist-info/RECORD
