Metadata-Version: 2.1
Name: review-ingest-app
Version: 1.0.1
Summary: A script to process reviews and generate aggregations.
License: MIT
Author: Prabhupad Pradhan
Author-email: prabhupad26@gmail.com
Requires-Python: >=3.8,<4.0
Classifier: License :: OSI Approved :: MIT License
Classifier: Programming Language :: Python :: 3
Classifier: Programming Language :: Python :: 3.8
Classifier: Programming Language :: Python :: 3.9
Classifier: Programming Language :: Python :: 3.10
Classifier: Programming Language :: Python :: 3.11
Classifier: Programming Language :: Python :: 3.12
Requires-Dist: PyYAML (>=6.0,<7.0)
Requires-Dist: argparse (>=1.4.0,<2.0.0)
Requires-Dist: pydantic (>=2.7.1,<3.0.0)
Requires-Dist: pytest (>=8.2.1,<9.0.0)
Requires-Dist: python-dateutil (>=2.9.0,<3.0.0)
Requires-Dist: pytz (>=2024.1,<2025.0)
Requires-Dist: rapidfuzz (>=3.9.1,<4.0.0)
Requires-Dist: tqdm (>=4.66.4,<5.0.0)
